{
  "updateDate": "2023-05-10T12:25UTC+08:00",
  "total": {
    "activeUsers": 59179,
    "screenPageViews": 135454,
    "userEngagementDuration": 5478130,
    "readingDuration": 5478130,
    "humanizedReadingDuration": "63 days, 9h 42m 10s",
    "readingDurationPerUser": 92,
    "humanizedReadingDurationPerUser": "01m 32s"
  },
  "trendingThisMonth": [
    {
      "pageTitle": "写给开发人员的实用密码学（五）—— 密钥交换 DHKE 与完美前向保密 PFS",
      "pagePath": "/posts/practical-cryptography-basics-5-key-exchange/",
      "activeUsers": 256,
      "screenPageViews": 398,
      "userEngagementDuration": 56729,
      "readingDuration": 56729,
      "humanizedReadingDuration": "15h 45m 29s",
      "readingDurationPerUser": 221,
      "humanizedReadingDurationPerUser": "03m 41s"
    },
    {
      "pageTitle": "写给开发人员的实用密码学（三）—— MAC 与密钥派生函数 KDF",
      "pagePath": "/posts/practical-cryptography-basics-3-key-derivation-function/",
      "activeUsers": 272,
      "screenPageViews": 477,
      "userEngagementDuration": 40306,
      "readingDuration": 40306,
      "humanizedReadingDuration": "11h 11m 46s",
      "readingDurationPerUser": 148,
      "humanizedReadingDurationPerUser": "02m 28s"
    },
    {
      "pageTitle": "写给开发人员的实用密码学（八）—— 数字证书与 TLS 协议",
      "pagePath": "/posts/about-tls-cert",
      "activeUsers": 312,
      "screenPageViews": 487,
      "userEngagementDuration": 44010,
      "readingDuration": 44010,
      "humanizedReadingDuration": "12h 13m 30s",
      "readingDurationPerUser": 141,
      "humanizedReadingDurationPerUser": "02m 21s"
    },
    {
      "pageTitle": "NixOS 与 Nix Flakes 新手入门",
      "pagePath": "/posts/nixos-and-flake-basics/",
      "activeUsers": 202,
      "screenPageViews": 267,
      "userEngagementDuration": 28532,
      "readingDuration": 28532,
      "humanizedReadingDuration": "7h 55m 32s",
      "readingDurationPerUser": 141,
      "humanizedReadingDurationPerUser": "02m 21s"
    },
    {
      "pageTitle": "NAT 网关、NAT 穿越以及虚拟网络",
      "pagePath": "/posts/about-nat/",
      "activeUsers": 233,
      "screenPageViews": 319,
      "userEngagementDuration": 31669,
      "readingDuration": 31669,
      "humanizedReadingDuration": "8h 47m 49s",
      "readingDurationPerUser": 135,
      "humanizedReadingDurationPerUser": "02m 15s"
    },
    {
      "pageTitle": "写给开发人员的实用密码学（四）—— 安全随机数生成器 CSPRNG",
      "pagePath": "/posts/practical-cryptography-basics-4-secure-random-generators/",
      "activeUsers": 228,
      "screenPageViews": 331,
      "userEngagementDuration": 30646,
      "readingDuration": 30646,
      "humanizedReadingDuration": "8h 30m 46s",
      "readingDurationPerUser": 134,
      "humanizedReadingDurationPerUser": "02m 14s"
    },
    {
      "pageTitle": "写给开发人员的实用密码学（二）—— 哈希函数",
      "pagePath": "/posts/practical-cryptography-basics-2-hash/",
      "activeUsers": 417,
      "screenPageViews": 600,
      "userEngagementDuration": 53830,
      "readingDuration": 53830,
      "humanizedReadingDuration": "14h 57m 10s",
      "readingDurationPerUser": 129,
      "humanizedReadingDurationPerUser": "02m 09s"
    },
    {
      "pageTitle": "EE 入门（一） - 电子电路基础知识",
      "pagePath": "/posts/electrical-engineering-circuits-basics-1/",
      "activeUsers": 231,
      "screenPageViews": 352,
      "userEngagementDuration": 29975,
      "readingDuration": 29975,
      "humanizedReadingDuration": "8h 19m 35s",
      "readingDurationPerUser": 129,
      "humanizedReadingDurationPerUser": "02m 09s"
    },
    {
      "pageTitle": "写给开发人员的实用密码学（七）—— 非对称密钥加密算法 RSA/ECC",
      "pagePath": "/posts/practical-cryptography-basics-7-asymmetric-key-ciphers/",
      "activeUsers": 511,
      "screenPageViews": 782,
      "userEngagementDuration": 64852,
      "readingDuration": 64852,
      "humanizedReadingDuration": "18h 52s",
      "readingDurationPerUser": 126,
      "humanizedReadingDurationPerUser": "02m 06s"
    },
    {
      "pageTitle": "2021 年年终总结",
      "pagePath": "/posts/2021-summary/",
      "activeUsers": 42,
      "screenPageViews": 60,
      "userEngagementDuration": 5304,
      "readingDuration": 5304,
      "humanizedReadingDuration": "1h 28m 24s",
      "readingDurationPerUser": 126,
      "humanizedReadingDurationPerUser": "02m 06s"
    },
    {
      "pageTitle": "2022 年年终总结",
      "pagePath": "/posts/2022-summary/",
      "activeUsers": 264,
      "screenPageViews": 356,
      "userEngagementDuration": 33210,
      "readingDuration": 33210,
      "humanizedReadingDuration": "9h 13m 30s",
      "readingDurationPerUser": 125,
      "humanizedReadingDurationPerUser": "02m 05s"
    },
    {
      "pageTitle": "使用 Istio 进行 JWT 身份验证（充当 API 网关）",
      "pagePath": "/posts/use-istio-for-jwt-auth/",
      "activeUsers": 56,
      "screenPageViews": 86,
      "userEngagementDuration": 6849,
      "readingDuration": 6849,
      "humanizedReadingDuration": "1h 54m 09s",
      "readingDurationPerUser": 122,
      "humanizedReadingDurationPerUser": "02m 02s"
    },
    {
      "pageTitle": "iptables 及 docker 容器网络分析",
      "pagePath": "/posts/iptables-and-container-networks/",
      "activeUsers": 350,
      "screenPageViews": 537,
      "userEngagementDuration": 41884,
      "readingDuration": 41884,
      "humanizedReadingDuration": "11h 38m 04s",
      "readingDurationPerUser": 119,
      "humanizedReadingDurationPerUser": "01m 59s"
    },
    {
      "pageTitle": "云原生流水线 Argo Workflows 的安装、使用以及个人体验",
      "pagePath": "/posts/experience-of-argo-workflows/",
      "activeUsers": 362,
      "screenPageViews": 579,
      "userEngagementDuration": 41384,
      "readingDuration": 41384,
      "humanizedReadingDuration": "11h 29m 44s",
      "readingDurationPerUser": 114,
      "humanizedReadingDurationPerUser": "01m 54s"
    },
    {
      "pageTitle": "Base64 编码并不唯一",
      "pagePath": "/posts/base64-encoding-is-not-unique/",
      "activeUsers": 24,
      "screenPageViews": 28,
      "userEngagementDuration": 2657,
      "readingDuration": 2657,
      "humanizedReadingDuration": "44m 17s",
      "readingDurationPerUser": 110,
      "humanizedReadingDurationPerUser": "01m 50s"
    },
    {
      "pageTitle": "Proxmox Virtual Environment 使用指南",
      "pagePath": "/posts/proxmox-virtual-environment-instruction/",
      "activeUsers": 888,
      "screenPageViews": 1227,
      "userEngagementDuration": 95364,
      "readingDuration": 95364,
      "humanizedReadingDuration": "1 day, 2h 29m 24s",
      "readingDurationPerUser": 107,
      "humanizedReadingDurationPerUser": "01m 47s"
    },
    {
      "pageTitle": "写给开发人员的实用密码学（六）—— 对称密钥加密算法",
      "pagePath": "/posts/practical-cryptography-basics-6-symmetric-key-ciphers/",
      "activeUsers": 532,
      "screenPageViews": 768,
      "userEngagementDuration": 57366,
      "readingDuration": 57366,
      "humanizedReadingDuration": "15h 56m 06s",
      "readingDurationPerUser": 107,
      "humanizedReadingDurationPerUser": "01m 47s"
    },
    {
      "pageTitle": "Kubernetes 微服务最佳实践",
      "pagePath": "/posts/kubernetes-best-practices/",
      "activeUsers": 151,
      "screenPageViews": 244,
      "userEngagementDuration": 15804,
      "readingDuration": 15804,
      "humanizedReadingDuration": "4h 23m 24s",
      "readingDurationPerUser": 104,
      "humanizedReadingDurationPerUser": "01m 44s"
    },
    {
      "pageTitle": "「转」且看有思想的年轻人",
      "pagePath": "/posts/the-thoughtful-youth/",
      "activeUsers": 21,
      "screenPageViews": 22,
      "userEngagementDuration": 2194,
      "readingDuration": 2194,
      "humanizedReadingDuration": "36m 34s",
      "readingDurationPerUser": 104,
      "humanizedReadingDurationPerUser": "01m 44s"
    },
    {
      "pageTitle": "Learn English Again",
      "pagePath": "/posts/learn-english-again/",
      "activeUsers": 261,
      "screenPageViews": 355,
      "userEngagementDuration": 26712,
      "readingDuration": 26712,
      "humanizedReadingDuration": "7h 25m 12s",
      "readingDurationPerUser": 102,
      "humanizedReadingDurationPerUser": "01m 42s"
    },
    {
      "pageTitle": "secrets 管理工具 Vault 的介绍、安装及使用",
      "pagePath": "/posts/experience-of-vault/",
      "activeUsers": 410,
      "screenPageViews": 643,
      "userEngagementDuration": 41665,
      "readingDuration": 41665,
      "humanizedReadingDuration": "11h 34m 25s",
      "readingDurationPerUser": 101,
      "humanizedReadingDurationPerUser": "01m 41s"
    },
    {
      "pageTitle": "变革与创新",
      "pagePath": "/posts/revolution-and-innovation/",
      "activeUsers": 21,
      "screenPageViews": 23,
      "userEngagementDuration": 2024,
      "readingDuration": 2024,
      "humanizedReadingDuration": "33m 44s",
      "readingDurationPerUser": 96,
      "humanizedReadingDurationPerUser": "01m 36s"
    },
    {
      "pageTitle": "SQLAlchemy 学习笔记（三）：ORM 中的关系构建",
      "pagePath": "/posts/sqlalchemy-notes-3-relationship-and-foreignkey/",
      "activeUsers": 32,
      "screenPageViews": 47,
      "userEngagementDuration": 2975,
      "readingDuration": 2975,
      "humanizedReadingDuration": "49m 35s",
      "readingDurationPerUser": 92,
      "humanizedReadingDurationPerUser": "01m 32s"
    },
    {
      "pageTitle": "FinOps for Kubernetes - 如何拆分 Kubernetes 成本",
      "pagePath": "/posts/finops-for-kubernetes/",
      "activeUsers": 115,
      "screenPageViews": 213,
      "userEngagementDuration": 10471,
      "readingDuration": 10471,
      "humanizedReadingDuration": "2h 54m 31s",
      "readingDurationPerUser": 91,
      "humanizedReadingDurationPerUser": "01m 31s"
    },
    {
      "pageTitle": "Linux 中的虚拟网络接口",
      "pagePath": "/posts/linux-virtual-network-interfaces/",
      "activeUsers": 348,
      "screenPageViews": 567,
      "userEngagementDuration": 31339,
      "readingDuration": 31339,
      "humanizedReadingDuration": "8h 42m 19s",
      "readingDurationPerUser": 90,
      "humanizedReadingDurationPerUser": "01m 30s"
    },
    {
      "pageTitle": "Kubernetes 中的证书管理工具 - cert-manager",
      "pagePath": "/posts/kubernetes-cert-management/",
      "activeUsers": 213,
      "screenPageViews": 275,
      "userEngagementDuration": 18911,
      "readingDuration": 18911,
      "humanizedReadingDuration": "5h 15m 11s",
      "readingDurationPerUser": 88,
      "humanizedReadingDurationPerUser": "01m 28s"
    },
    {
      "pageTitle": "WebSocket、HTTP/2 与 gRPC",
      "pagePath": "/posts/websocket-http2-and-grpc/",
      "activeUsers": 86,
      "screenPageViews": 94,
      "userEngagementDuration": 7179,
      "readingDuration": 7179,
      "humanizedReadingDuration": "1h 59m 39s",
      "readingDurationPerUser": 83,
      "humanizedReadingDurationPerUser": "01m 23s"
    },
    {
      "pageTitle": "我在创业公司做技术一年多的一点体会",
      "pagePath": "/posts/end-of-the-first-round/",
      "activeUsers": 62,
      "screenPageViews": 68,
      "userEngagementDuration": 5121,
      "readingDuration": 5121,
      "humanizedReadingDuration": "1h 25m 21s",
      "readingDurationPerUser": 82,
      "humanizedReadingDurationPerUser": "01m 22s"
    },
    {
      "pageTitle": "2020 年年终总结",
      "pagePath": "/posts/2020-summary/",
      "activeUsers": 36,
      "screenPageViews": 44,
      "userEngagementDuration": 2952,
      "readingDuration": 2952,
      "humanizedReadingDuration": "49m 12s",
      "readingDurationPerUser": 82,
      "humanizedReadingDurationPerUser": "01m 22s"
    },
    {
      "pageTitle": "脚踏实地，仰望星空",
      "pagePath": "/posts/no-more-dreams/",
      "activeUsers": 23,
      "screenPageViews": 28,
      "userEngagementDuration": 1897,
      "readingDuration": 1897,
      "humanizedReadingDuration": "31m 37s",
      "readingDurationPerUser": 82,
      "humanizedReadingDurationPerUser": "01m 22s"
    },
    {
      "pageTitle": "Linux 上的 WireGuard 网络分析（一）",
      "pagePath": "/posts/wireguard-on-linux/",
      "activeUsers": 70,
      "screenPageViews": 90,
      "userEngagementDuration": 5439,
      "readingDuration": 5439,
      "humanizedReadingDuration": "1h 30m 39s",
      "readingDurationPerUser": 77,
      "humanizedReadingDurationPerUser": "01m 17s"
    },
    {
      "pageTitle": "Python 异步编程笔记：asyncio",
      "pagePath": "/posts/python-asyncio/",
      "activeUsers": 8,
      "screenPageViews": 7,
      "userEngagementDuration": 612,
      "readingDuration": 612,
      "humanizedReadingDuration": "10m 12s",
      "readingDurationPerUser": 76,
      "humanizedReadingDurationPerUser": "01m 16s"
    },
    {
      "pageTitle": "Java 中文编码分析",
      "pagePath": "/posts/how-java-handles-chinese/",
      "activeUsers": 6,
      "screenPageViews": 7,
      "userEngagementDuration": 461,
      "readingDuration": 461,
      "humanizedReadingDuration": "07m 41s",
      "readingDurationPerUser": 76,
      "humanizedReadingDurationPerUser": "01m 16s"
    },
    {
      "pageTitle": "写给开发人员的实用密码学（一）—— 概览",
      "pagePath": "/posts/practical-cryptography-basics-1/",
      "activeUsers": 380,
      "screenPageViews": 614,
      "userEngagementDuration": 28132,
      "readingDuration": 28132,
      "humanizedReadingDuration": "7h 48m 52s",
      "readingDurationPerUser": 74,
      "humanizedReadingDurationPerUser": "01m 14s"
    },
    {
      "pageTitle": "使用 tcpdump 和 Wireshark 进行远程实时抓包分析",
      "pagePath": "/posts/tcpdump-and-wireshark/",
      "activeUsers": 202,
      "screenPageViews": 313,
      "userEngagementDuration": 14468,
      "readingDuration": 14468,
      "humanizedReadingDuration": "4h 01m 08s",
      "readingDurationPerUser": 71,
      "humanizedReadingDurationPerUser": "01m 11s"
    },
    {
      "pageTitle": "Linux网络学习笔记（二）：域名解析(DNS)——以 CoreDNS 为例",
      "pagePath": "/posts/about-dns-protocol/",
      "activeUsers": 149,
      "screenPageViews": 207,
      "userEngagementDuration": 10603,
      "readingDuration": 10603,
      "humanizedReadingDuration": "2h 56m 43s",
      "readingDurationPerUser": 71,
      "humanizedReadingDurationPerUser": "01m 11s"
    },
    {
      "pageTitle": "Pulumi 使用体验 - 基础设施代码化",
      "pagePath": "/posts/experience-of-pulumi/",
      "activeUsers": 80,
      "screenPageViews": 101,
      "userEngagementDuration": 5757,
      "readingDuration": 5757,
      "humanizedReadingDuration": "1h 35m 57s",
      "readingDurationPerUser": 71,
      "humanizedReadingDurationPerUser": "01m 11s"
    },
    {
      "pageTitle": "欧几里得算法求最大公约数(GCD)的数学原理",
      "pagePath": "/posts/mathematics-in-euclidean-gcd/",
      "activeUsers": 41,
      "screenPageViews": 46,
      "userEngagementDuration": 2937,
      "readingDuration": 2937,
      "humanizedReadingDuration": "48m 57s",
      "readingDurationPerUser": 71,
      "humanizedReadingDurationPerUser": "01m 11s"
    },
    {
      "pageTitle": "SQLAlchemy 学习笔记（一）：Engine 与 SQL 表达式语言",
      "pagePath": "/posts/sqlalchemy-notes-1-engine-and-sql-expression-language/",
      "activeUsers": 49,
      "screenPageViews": 75,
      "userEngagementDuration": 3471,
      "readingDuration": 3471,
      "humanizedReadingDuration": "57m 51s",
      "readingDurationPerUser": 70,
      "humanizedReadingDurationPerUser": "01m 10s"
    },
    {
      "pageTitle": "2019 年年终总结",
      "pagePath": "/posts/2019-summary/",
      "activeUsers": 23,
      "screenPageViews": 27,
      "userEngagementDuration": 1582,
      "readingDuration": 1582,
      "humanizedReadingDuration": "26m 22s",
      "readingDurationPerUser": 68,
      "humanizedReadingDurationPerUser": "01m 08s"
    },
    {
      "pageTitle": "分布式数据库的一致性问题与共识算法",
      "pagePath": "/posts/consistency-and-consensus-algorithm/",
      "activeUsers": 299,
      "screenPageViews": 440,
      "userEngagementDuration": 19878,
      "readingDuration": 19878,
      "humanizedReadingDuration": "5h 31m 18s",
      "readingDurationPerUser": 66,
      "humanizedReadingDurationPerUser": "01m 06s"
    },
    {
      "pageTitle": "SQL 基础笔记（三）约束",
      "pagePath": "/posts/sql-basics-3-restrict/",
      "activeUsers": 6,
      "screenPageViews": 6,
      "userEngagementDuration": 391,
      "readingDuration": 391,
      "humanizedReadingDuration": "06m 31s",
      "readingDurationPerUser": 65,
      "humanizedReadingDurationPerUser": "01m 05s"
    },
    {
      "pageTitle": "QEMU/KVM 虚拟化环境的搭建与使用",
      "pagePath": "/posts/qemu-kvm-usage/",
      "activeUsers": 684,
      "screenPageViews": 980,
      "userEngagementDuration": 44429,
      "readingDuration": 44429,
      "humanizedReadingDuration": "12h 20m 29s",
      "readingDurationPerUser": 64,
      "humanizedReadingDurationPerUser": "01m 04s"
    },
    {
      "pageTitle": "部署一个 Kubernetes 集群",
      "pagePath": "/posts/kubernetes-deployment-using-kubeadm/",
      "activeUsers": 60,
      "screenPageViews": 81,
      "userEngagementDuration": 3803,
      "readingDuration": 3803,
      "humanizedReadingDuration": "1h 03m 23s",
      "readingDurationPerUser": 63,
      "humanizedReadingDurationPerUser": "01m 03s"
    },
    {
      "pageTitle": "Manjaro 使用指南",
      "pagePath": "/posts/manjaro-instruction/",
      "activeUsers": 43,
      "screenPageViews": 52,
      "userEngagementDuration": 2690,
      "readingDuration": 2690,
      "humanizedReadingDuration": "44m 50s",
      "readingDurationPerUser": 62,
      "humanizedReadingDurationPerUser": "01m 02s"
    },
    {
      "pageTitle": "瘾的退却",
      "pagePath": "/posts/webnovel-addiction-recovery/",
      "activeUsers": 9,
      "screenPageViews": 11,
      "userEngagementDuration": 564,
      "readingDuration": 564,
      "humanizedReadingDuration": "09m 24s",
      "readingDurationPerUser": 62,
      "humanizedReadingDurationPerUser": "01m 02s"
    },
    {
      "pageTitle": "Linux/Windows/MacOSX 系统常用命令集锦",
      "pagePath": "/posts/common-commands-for-various-operating-systems/",
      "activeUsers": 123,
      "screenPageViews": 134,
      "userEngagementDuration": 6831,
      "readingDuration": 6831,
      "humanizedReadingDuration": "1h 53m 51s",
      "readingDurationPerUser": 55,
      "humanizedReadingDurationPerUser": "55s"
    },
    {
      "pageTitle": "EE 入门（二） - 使用 ESP32 与 SPI 显示屏绘图、显示图片、跑贪吃蛇",
      "pagePath": "/posts/ee-basics-2-esp32-display/",
      "activeUsers": 110,
      "screenPageViews": 158,
      "userEngagementDuration": 6159,
      "readingDuration": 6159,
      "humanizedReadingDuration": "1h 42m 39s",
      "readingDurationPerUser": 55,
      "humanizedReadingDurationPerUser": "55s"
    },
    {
      "pageTitle": "openSUSE 使用指南",
      "pagePath": "/posts/opensuse-instruction/",
      "activeUsers": 118,
      "screenPageViews": 143,
      "userEngagementDuration": 6317,
      "readingDuration": 6317,
      "humanizedReadingDuration": "1h 45m 17s",
      "readingDurationPerUser": 53,
      "humanizedReadingDurationPerUser": "53s"
    },
    {
      "pageTitle": "JWT 签名算法 HS256、RS256 及 ES256 及密钥生成",
      "pagePath": "/posts/jwt-algorithm-key-generation/",
      "activeUsers": 346,
      "screenPageViews": 433,
      "userEngagementDuration": 17801,
      "readingDuration": 17801,
      "humanizedReadingDuration": "4h 56m 41s",
      "readingDurationPerUser": 51,
      "humanizedReadingDurationPerUser": "51s"
    },
    {
      "pageTitle": "Linux 网络工具中的瑞士军刀 - socat & netcat",
      "pagePath": "/posts/socat-netcat/",
      "activeUsers": 185,
      "screenPageViews": 248,
      "userEngagementDuration": 8159,
      "readingDuration": 8159,
      "humanizedReadingDuration": "2h 15m 59s",
      "readingDurationPerUser": 44,
      "humanizedReadingDurationPerUser": "44s"
    },
    {
      "pageTitle": "Python 并发编程：PoolExecutor 篇",
      "pagePath": "/posts/python-concurrency-pool-executor/",
      "activeUsers": 18,
      "screenPageViews": 20,
      "userEngagementDuration": 768,
      "readingDuration": 768,
      "humanizedReadingDuration": "12m 48s",
      "readingDurationPerUser": 42,
      "humanizedReadingDurationPerUser": "42s"
    },
    {
      "pageTitle": "月宫",
      "pagePath": "/posts/moon-palace/",
      "activeUsers": 8,
      "screenPageViews": 8,
      "userEngagementDuration": 337,
      "readingDuration": 337,
      "humanizedReadingDuration": "05m 37s",
      "readingDurationPerUser": 42,
      "humanizedReadingDurationPerUser": "42s"
    },
    {
      "pageTitle": "Kubernetes 常见错误、原因及处理方法",
      "pagePath": "/posts/kubernetes-common-errors-and-solutions/",
      "activeUsers": 293,
      "screenPageViews": 354,
      "userEngagementDuration": 12235,
      "readingDuration": 12235,
      "humanizedReadingDuration": "3h 23m 55s",
      "readingDurationPerUser": 41,
      "humanizedReadingDurationPerUser": "41s"
    },
    {
      "pageTitle": "刻意练习",
      "pagePath": "/posts/deliberate-practice/",
      "activeUsers": 101,
      "screenPageViews": 117,
      "userEngagementDuration": 4206,
      "readingDuration": 4206,
      "humanizedReadingDuration": "1h 10m 06s",
      "readingDurationPerUser": 41,
      "humanizedReadingDurationPerUser": "41s"
    },
    {
      "pageTitle": "进程线程协程与并发并行",
      "pagePath": "/posts/process-thread-coroutines-concurrency-parallelism/",
      "activeUsers": 18,
      "screenPageViews": 21,
      "userEngagementDuration": 746,
      "readingDuration": 746,
      "humanizedReadingDuration": "12m 26s",
      "readingDurationPerUser": 41,
      "humanizedReadingDurationPerUser": "41s"
    },
    {
      "pageTitle": "SQLAlchemy 学习笔记（二）：ORM 基础",
      "pagePath": "/posts/sqlalchemy-notes-2-orm-basics/",
      "activeUsers": 22,
      "screenPageViews": 29,
      "userEngagementDuration": 862,
      "readingDuration": 862,
      "humanizedReadingDuration": "14m 22s",
      "readingDurationPerUser": 39,
      "humanizedReadingDurationPerUser": "39s"
    },
    {
      "pageTitle": "逃离我的大学",
      "pagePath": "/posts/escape-my-university/",
      "activeUsers": 50,
      "screenPageViews": 53,
      "userEngagementDuration": 1852,
      "readingDuration": 1852,
      "humanizedReadingDuration": "30m 52s",
      "readingDurationPerUser": 37,
      "humanizedReadingDurationPerUser": "37s"
    },
    {
      "pageTitle": "学英语啊学英语",
      "pagePath": "/posts/learning-english/",
      "activeUsers": 30,
      "screenPageViews": 34,
      "userEngagementDuration": 1076,
      "readingDuration": 1076,
      "humanizedReadingDuration": "17m 56s",
      "readingDurationPerUser": 35,
      "humanizedReadingDurationPerUser": "35s"
    },
    {
      "pageTitle": "我患上了阅读焦虑症",
      "pagePath": "/posts/reading-anxiety/",
      "activeUsers": 11,
      "screenPageViews": 14,
      "userEngagementDuration": 351,
      "readingDuration": 351,
      "humanizedReadingDuration": "05m 51s",
      "readingDurationPerUser": 31,
      "humanizedReadingDurationPerUser": "31s"
    },
    {
      "pageTitle": "常见压缩格式的区别，及 Linux 下的压缩相关指令",
      "pagePath": "/posts/compression-related-instructions-under-linux/",
      "activeUsers": 11,
      "screenPageViews": 12,
      "userEngagementDuration": 308,
      "readingDuration": 308,
      "humanizedReadingDuration": "05m 08s",
      "readingDurationPerUser": 28,
      "humanizedReadingDurationPerUser": "28s"
    },
    {
      "pageTitle": "Death Is But a Dream",
      "pagePath": "/posts/death-is-but-a-dream/",
      "activeUsers": 17,
      "screenPageViews": 20,
      "userEngagementDuration": 444,
      "readingDuration": 444,
      "humanizedReadingDuration": "07m 24s",
      "readingDurationPerUser": 26,
      "humanizedReadingDurationPerUser": "26s"
    },
    {
      "pageTitle": "Python 实用技巧与常见错误集锦",
      "pagePath": "/posts/python-tips-and-tricks/",
      "activeUsers": 31,
      "screenPageViews": 40,
      "userEngagementDuration": 758,
      "readingDuration": 758,
      "humanizedReadingDuration": "12m 38s",
      "readingDurationPerUser": 24,
      "humanizedReadingDurationPerUser": "24s"
    },
    {
      "pageTitle": "「转」仙马赛记——我又 PB 了",
      "pagePath": "/posts/likenttt-2021-04-11-xianlin-half-marathon-1_33_12/",
      "activeUsers": 19,
      "screenPageViews": 22,
      "userEngagementDuration": 373,
      "readingDuration": 373,
      "humanizedReadingDuration": "06m 13s",
      "readingDurationPerUser": 19,
      "humanizedReadingDurationPerUser": "19s"
    },
    {
      "pageTitle": "《十二国记》",
      "pagePath": "/posts/the-twelve-kingdoms/",
      "activeUsers": 19,
      "screenPageViews": 19,
      "userEngagementDuration": 320,
      "readingDuration": 320,
      "humanizedReadingDuration": "05m 20s",
      "readingDurationPerUser": 16,
      "humanizedReadingDurationPerUser": "16s"
    }
  ]
}